epicbox/__init__.py
epicbox/config.py
epicbox/exceptions.py
epicbox/sandboxes.py
epicbox/session.py
epicbox/utils.py
epicbox/working_directory.py
epicbox2-2.0.0.dist-info/LICENSE
epicbox2-2.0.0.dist-info/METADATA
epicbox2-2.0.0.dist-info/WHEEL
epicbox2-2.0.0.dist-info/top_level.txt
epicbox2-2.0.0.dist-info/RECORD
