Metadata-Version: 2.1
Name: epicbox2
Version: 2.0.0
Summary: EpicBox runs untrusted code in secure Docker based sandboxes
Author: Pavel Sviderski <ps@stepik.org>, Claudio Spiess
License: MIT License
Project-URL: Homepage, https://github.com/claudiosv/epicbox2
Keywords: docker,sandbox
Classifier: Topic :: Software Development :: Libraries :: Python Modules
Requires-Python: >=3.10
License-File: LICENSE
Requires-Dist: docker >=7.0.0
Requires-Dist: python-dateutil ~=2.9.0
Requires-Dist: requests >=2.31
Requires-Dist: structlog >=24.1.0
Provides-Extra: dev
Requires-Dist: ruff >=0.2.2 ; extra == 'dev'
Requires-Dist: pytest ~=7.4.2 ; extra == 'dev'
Requires-Dist: pytest-cov ~=4.1.0 ; extra == 'dev'
